mka_eureka_microservice_controllers/__init__.py
mka_eureka_microservice_controllers/shared_scripts/__init__.py
mka_eureka_microservice_controllers/shared_scripts/mka_base64_converter.py
mka_eureka_microservice_controllers/shared_scripts/mka_processing.py
mka_eureka_microservice_controllers/shared_scripts/mka_requests.py
mka_eureka_microservice_controllers/shared_scripts/mka_responses.py
mka_eureka_microservice_controllers/shared_scripts/mka_services_managment.py
mka_eureka_microservice_controllers/shared_scripts/mka_shared_settings.py
mka_eureka_microservice_controllers/shared_scripts/mka_terms_definition.py
mka_eureka_microservice_controllers-0.5.0.dist-info/LICENSE
mka_eureka_microservice_controllers-0.5.0.dist-info/METADATA
mka_eureka_microservice_controllers-0.5.0.dist-info/WHEEL
mka_eureka_microservice_controllers-0.5.0.dist-info/entry_points.txt
mka_eureka_microservice_controllers-0.5.0.dist-info/top_level.txt
mka_eureka_microservice_controllers-0.5.0.dist-info/RECORD
