Metadata-Version: 2.1
Name: mka-eureka-microservice-controllers
Version: 0.5.0
Summary: A package contains scripts to easily connection between connected django microservice with eureka
Home-page: 
Author: Adnan Aji
Author-email: 
Classifier: Programming Language :: Python :: 3
Classifier: License :: OSI Approved :: MIT License
Requires-Python: >=3.6
License-File: LICENSE
